LICENSE.txt
MANIFEST.in
README.rst
RELEASE-VERSION
setup.py
version.py
src/pyconnectedcomponent/__init__.py
src/pyconnectedcomponent.egg-info/PKG-INFO
src/pyconnectedcomponent.egg-info/SOURCES.txt
src/pyconnectedcomponent.egg-info/dependency_links.txt
src/pyconnectedcomponent.egg-info/requires.txt
src/pyconnectedcomponent.egg-info/top_level.txt
src/tests/__init__.py
src/tests/pyconnectedcomponent/__init__.py
src/tests/pyconnectedcomponent/test_cc.py