Metadata-Version: 1.1
Name: pyconnectedcomponent
Version: 0.1.3.dev1
Summary: simple connected component tool from http://breakingcode.wordpress.com/2013/04/08/finding-connected-components-in-a-graph/
Home-page: http://breakingcode.wordpress.com/2013/04/08/finding-connected-components-in-a-graph/
Author: Diffeo, Inc.
Author-email: support@diffeo.com
License: UNKNOWN
Platform: UNKNOWN
Classifier: Development Status :: 3 - Alpha
Classifier: Topic :: Utilities
Classifier: License :: OSI Approved :: MIT License
